propagsim/__init__.py
propagsim/classes.py
propagsim/utils.py
propagsim-0.2.dist-info/LICENSE
propagsim-0.2.dist-info/METADATA
propagsim-0.2.dist-info/WHEEL
propagsim-0.2.dist-info/top_level.txt
propagsim-0.2.dist-info/RECORD
