Metadata-Version: 2.1
Name: propagsim
Version: 0.2
Summary: Implementation of CAST propagation model
Home-page: https://github.com/parcoor/py-propagsim
Author: Manuel Capel
Author-email: manuel.capel@parcoor.com
License: UNKNOWN
Platform: UNKNOWN
Classifier: Programming Language :: Python :: 3
Classifier: License :: OSI Approved :: MIT License
Classifier: Operating System :: OS Independent
